agentcomlink/__init__.py
agentcomlink/constants.py
agentcomlink/files.py
agentcomlink/page.py
agentcomlink/server.py
agentcomlink-0.1.11.dist-info/LICENSE
agentcomlink-0.1.11.dist-info/METADATA
agentcomlink-0.1.11.dist-info/WHEEL
agentcomlink-0.1.11.dist-info/top_level.txt
agentcomlink-0.1.11.dist-info/RECORD
