Metadata-Version: 2.1
Name: agentcomlink
Version: 0.1.11
Summary: Simple chat, debug and file management panel for agents
Home-page: https://github.com/AutonomousResearchGroup/agentcomlink
Author: Moon
Author-email: shawmakesmagic@gmail.com
License: MIT
Classifier: Development Status :: 4 - Beta
Classifier: Intended Audience :: Science/Research
Classifier: License :: OSI Approved :: MIT License
Classifier: Operating System :: POSIX :: Linux
Classifier: Programming Language :: Python :: 3
Classifier: Operating System :: MacOS :: MacOS X
Classifier: Operating System :: Microsoft :: Windows
License-File: LICENSE
Requires-Dist: chromadb
Requires-Dist: rich
